autopilotrpc/__init__.py
autopilotrpc/autopilot_pb2.py
autopilotrpc/autopilot_pb2_grpc.py
chainrpc/__init__.py
chainrpc/chainnotifier_pb2.py
chainrpc/chainnotifier_pb2_grpc.py
invoicesrpc/__init__.py
invoicesrpc/invoices_pb2.py
invoicesrpc/invoices_pb2_grpc.py
lnclipb/__init__.py
lnclipb/lncli_pb2.py
lnclipb/lncli_pb2_grpc.py
lnrpc/__init__.py
lnrpc/rpc_pb2.py
lnrpc/rpc_pb2_grpc.py
routerrpc/__init__.py
routerrpc/router_pb2.py
routerrpc/router_pb2_grpc.py
signrpc/__init__.py
signrpc/signer_pb2.py
signrpc/signer_pb2_grpc.py
verrpc/__init__.py
verrpc/verrpc_pb2.py
verrpc/verrpc_pb2_grpc.py
walletrpc/__init__.py
walletrpc/walletkit_pb2.py
walletrpc/walletkit_pb2_grpc.py
watchtowerrpc/__init__.py
watchtowerrpc/watchtower_pb2.py
watchtowerrpc/watchtower_pb2_grpc.py
wtclientrpc/__init__.py
wtclientrpc/wtclient_pb2.py
wtclientrpc/wtclient_pb2_grpc.py
lnd_rpc-0.10.0.post12.dist-info/LICENSE
lnd_rpc-0.10.0.post12.dist-info/METADATA
lnd_rpc-0.10.0.post12.dist-info/WHEEL
lnd_rpc-0.10.0.post12.dist-info/top_level.txt
lnd_rpc-0.10.0.post12.dist-info/RECORD
