Metadata-Version: 2.1
Name: lnd-rpc
Version: 0.10.0.post12
Summary: gRPC bindings for various lnd versions
Home-page: https://github.com/lncm/lnd-rpc
Author: Damian Mee
Author-email: bugs@meedamian.com
License: MIT
Keywords: ln,lnd,grpc,proto
Platform: UNKNOWN
Classifier: License :: OSI Approved :: MIT License
Classifier: Programming Language :: Python :: 3
Classifier: Programming Language :: Python :: 3.5
Requires-Dist: google-api-core
Requires-Dist: googleapis-common-protos
Requires-Dist: grpcio
Requires-Dist: protobuf
